gnewsclient/PyOpenGraph.py
gnewsclient/gnewsclient.py
gnewsclient/utils.py
gnewsclient-1.12.dist-info/METADATA
gnewsclient-1.12.dist-info/RECORD
gnewsclient-1.12.dist-info/WHEEL
gnewsclient-1.12.dist-info/top_level.txt
