Metadata-Version: 2.1
Name: gnewsclient
Version: 1.12
Summary: Python client for Google News Feed.
Home-page: http://github.com/nikhilkumarsingh/gnewsclient
Author: Nikhil Kumar Singh
Author-email: nikhilksingh97@gmail.com
License: MIT
Keywords: google news feed python client feed
Platform: UNKNOWN
Classifier: License :: OSI Approved :: MIT License
Classifier: Programming Language :: Python :: 3
Classifier: Programming Language :: Python :: 3.7
